pyprexor/__init__.py
pyprexor/core.py
pyprexor_datastore/__init__.py
pyprexor_datastore/datastore.py
pyprexor_datastore/mongo.py
pyprexor-1.1.0.dist-info/LICENSE
pyprexor-1.1.0.dist-info/METADATA
pyprexor-1.1.0.dist-info/WHEEL
pyprexor-1.1.0.dist-info/RECORD
