Metadata-Version: 2.1
Name: pyprexor
Version: 1.1.0
Summary: 
Home-page: https://github.com/NickSebClark/pyprexor
Author: _MircoWave_
Author-email: clarknick1990@gmail.com
Requires-Python: >=3.9,<4.0
Classifier: Programming Language :: Python :: 3
Classifier: Programming Language :: Python :: 3.9
Classifier: Programming Language :: Python :: 3.10
Classifier: Programming Language :: Python :: 3.11
Project-URL: Repository, https://github.com/NickSebClark/pyprexor
